{
  "version": 12,
  "mae_walk_forward": 179.992373585589,
  "r2_train": 0.9548711104371993,
  "mae_train": 88.48923579377946,
  "rmse_train": 124.74886685787234,
  "ratio_wf_train": 2.0341,
  "overfitting_flag": "ok",
  "best_params": {
    "max_depth": 4,
    "min_child_weight": 7,
    "subsample": 0.7011893548856963,
    "colsample_bytree": 0.5081075865881999,
    "reg_alpha": 4.1290232969463965,
    "reg_lambda": 6.99543702887235,
    "learning_rate": 0.02644984682683573,
    "num_boost_round": 269
  },
  "feature_names": [
    "usuarios_registro_base",
    "tasa_basic_a_risk",
    "tasa_risk_a_fulldata",
    "tasa_fulldata_a_video",
    "tasa_video_a_review",
    "tasa_review_a_aprobado",
    "tasa_registro_a_aprobado",
    "mediana_dias_registro_a_full",
    "pct_perfil_conservador",
    "pct_perfil_arriesgado",
    "push_mail_delivered_pre_deposito",
    "cx_friccion_kyc",
    "cx_bloqueos",
    "Tasa_Intervencion_Mensual",
    "TRM",
    "Variacion_COLCAP",
    "semana_del_mes",
    "semana_del_mes_proyeccion",
    "dias_habiles_semana",
    "mes_prima",
    "dias_habiles_proyeccion",
    "registros_ponderados",
    "aprobados_ponderados",
    "lag_1_target",
    "full_users_aprobados_lag1",
    "tendencia_registros_4w",
    "tendencia_aprobados_4w",
    "tendencia_depositos_4w",
    "tasa_registro_a_aprobado_ewma_4",
    "tasa_rechazo_implicita_kyc_ewma_4"
  ],
  "n_samples": 265,
  "n_features": 30,
  "feature_importance": {
    "cx_bloqueos": 3897784.0,
    "lag_1_target": 2748002.25,
    "cx_friccion_kyc": 1542295.125,
    "registros_ponderados": 813588.9375,
    "aprobados_ponderados": 731176.875,
    "tasa_risk_a_fulldata": 638176.3125,
    "usuarios_registro_base": 473466.0625,
    "Tasa_Intervencion_Mensual": 288212.9688,
    "tasa_fulldata_a_video": 274602.3125,
    "Variacion_COLCAP": 175120.8125,
    "pct_perfil_conservador": 171540.8906,
    "tasa_basic_a_risk": 167222.2969,
    "pct_perfil_arriesgado": 164410.4219,
    "semana_del_mes": 163942.75,
    "tasa_rechazo_implicita_kyc_ewma_4": 156339.4531,
    "TRM": 148694.4844,
    "tasa_video_a_review": 147782.75,
    "push_mail_delivered_pre_deposito": 144660.3281,
    "mediana_dias_registro_a_full": 135947.4219,
    "full_users_aprobados_lag1": 123861.1406,
    "semana_del_mes_proyeccion": 118583.1953,
    "tasa_registro_a_aprobado_ewma_4": 115887.7656,
    "tasa_registro_a_aprobado": 109556.5156,
    "tendencia_registros_4w": 98679.0312,
    "dias_habiles_proyeccion": 95809.1953,
    "tasa_review_a_aprobado": 95111.8047,
    "tendencia_depositos_4w": 82066.625,
    "mes_prima": 80060.8281,
    "tendencia_aprobados_4w": 71376.7656,
    "dias_habiles_semana": 56429.6562
  },
  "status": "ok"
}